generate_sequences/__init__.py
generate_sequences/py.typed
generate_sequences/utils.py
generate_sequences/version.py
generate_sequences/generate/__init__.py
generate_sequences/generate/base.py
generate_sequences/generate/beam_search.py
generate_sequences/generate/greedy.py
generate_sequences-0.0.9.dist-info/LICENSE
generate_sequences-0.0.9.dist-info/METADATA
generate_sequences-0.0.9.dist-info/WHEEL
generate_sequences-0.0.9.dist-info/top_level.txt
generate_sequences-0.0.9.dist-info/RECORD
