Metadata-Version: 2.1
Name: generate-sequences
Version: 0.0.9
Author-email: "Maged S. Al-Shaibani" <mageedsaeed1@gmail.com>
License: Apache License
Project-URL: Homepage, https://github.com/MagedSaeed/generate-sequences
Project-URL: Repository, https://github.com/MagedSaeed/generate-sequences
Project-URL: Changelog, https://github.com/MagedSaeed/generate-sequences/blob/main/CHANGELOG.md
Classifier: Intended Audience :: Science/Research
Classifier: Development Status :: 3 - Alpha
Classifier: License :: OSI Approved :: Apache Software License
Classifier: Programming Language :: Python :: 3
Classifier: Topic :: Scientific/Engineering :: Artificial Intelligence
Requires-Python: >=3.8
License-File: LICENSE
Requires-Dist: tqdm ==4.66.*
Requires-Dist: numpy >=1.24.0
Requires-Dist: torch <2.4,>=2.2
Provides-Extra: dev
Requires-Dist: ruff ; extra == 'dev'
Requires-Dist: mypy <1.11,>=1.0 ; extra == 'dev'
Requires-Dist: black <25.0,>=23.0 ; extra == 'dev'
Requires-Dist: isort <5.14,>=5.12 ; extra == 'dev'
Requires-Dist: pytest ; extra == 'dev'
Requires-Dist: pytest-sphinx ; extra == 'dev'
Requires-Dist: pytest-cov ; extra == 'dev'
Requires-Dist: twine >=1.11.0 ; extra == 'dev'
Requires-Dist: build ; extra == 'dev'
Requires-Dist: setuptools ; extra == 'dev'
Requires-Dist: wheel ; extra == 'dev'
Requires-Dist: Sphinx <7.4.0,>=4.3.0 ; extra == 'dev'
Requires-Dist: furo ==2024.5.6 ; extra == 'dev'
Requires-Dist: myst-parser <3.1,>=1.0 ; extra == 'dev'
Requires-Dist: sphinx-copybutton ==0.5.2 ; extra == 'dev'
Requires-Dist: sphinx-autobuild ==2021.3.14 ; extra == 'dev'
Requires-Dist: sphinx-autodoc-typehints ==2.0.0 ; extra == 'dev'
Requires-Dist: packaging ; extra == 'dev'
Requires-Dist: pre-commit ==3.5.0 ; extra == 'dev'
Requires-Dist: evaluate ==0.4.* ; extra == 'dev'
Requires-Dist: sacrebleu ==2.4.* ; extra == 'dev'
Requires-Dist: sacremoses ==0.1.* ; extra == 'dev'
Requires-Dist: sentencepiece ==0.2.* ; extra == 'dev'
Requires-Dist: transformers <4.42,>=4.39 ; extra == 'dev'
